{
  "schema_version": "1.0",
  "generated_at_phase": 2,
  "fr_ids": [
    "FR-01",
    "FR-02",
    "FR-03",
    "FR-04",
    "FR-05"
  ],
  "nfr_dimension_mapping": {
    "NFR-01": "performance",
    "NFR-02": "security",
    "NFR-03": "error_handling",
    "NFR-04": "security",
    "NFR-05": "readability",
    "NFR-07": "error_handling",
    "NFR-08": "error_handling",
    "NFR-10": "readability"
  },
  "nfr_fr_mapping": {},
  "nfr_traceability": {
    "NFR-01": {
      "type": "performance",
      "target": "p95 < 50ms",
      "module": "taskq.storage.store"
    },
    "NFR-02": {
      "type": "security",
      "target": ">=100",
      "module": "taskq.interface.cli"
    },
    "NFR-03": {
      "type": "reliability",
      "target": ">=100",
      "module": "taskq.storage.store"
    },
    "NFR-04": {
      "type": "security",
      "target": ">=100",
      "module": "taskq.runtime.executor"
    },
    "NFR-05": {
      "type": "maintainability",
      "target": ">=100",
      "module": "taskq.core.models"
    },
    "NFR-06": {
      "type": "deployability",
      "target": ">=100",
      "module": "taskq.core.config"
    },
    "NFR-07": {
      "type": "reliability",
      "target": ">=100",
      "module": "taskq.storage.store"
    },
    "NFR-08": {
      "type": "reliability",
      "target": ">=100",
      "module": "taskq.storage.store"
    },
    "NFR-09": {
      "type": "scalability",
      "target": "p95 < 100ms @ 1000 tasks",
      "module": "taskq.storage.store"
    },
    "NFR-10": {
      "type": "maintainability",
      "target": ">=100",
      "module": "taskq.storage.store"
    }
  },
  "quality_targets": {
    "max_complexity": 15,
    "min_coverage": 80,
    "max_coupling": 0.3
  },
  "fr_module_traceability": {
    "FR-01": "taskq.storage.store",
    "FR-02": "taskq.runtime.executor",
    "FR-03": "taskq.storage.breaker",
    "FR-04": "taskq.storage.cache",
    "FR-05": "taskq.interface.cli"
  },
  "architecture_constraints": [
    "no_circular_dependencies",
    "no_shell_true",
    "atomic_write_all_data_files",
    "stream_iter_no_full_load",
    "no_silent_rebuild_or_silent_swallow_errors"
  ],
  "high_risk_modules": [
    "taskq.runtime.executor",
    "taskq.storage.store"
  ],
  "gate_score_overrides": {
    "performance": 75.0,
    "security": 100.0,
    "error_handling": 100.0,
    "readability": 100.0,
    "test_coverage": 80.0
  },
  "gate_results": {
    "gate1": {},
    "gate2": null,
    "gate3": null,
    "gate4": null
  }
}
